dcmagick/__init__.py
dcmagick/cli.py
dcmagick/common/__init__.py
dcmagick/common/context.py
dcmagick/common/dicom.py
dcmagick/common/exception.py
dcmagick/common/format.py
dcmagick/common/improc.py
dcmagick/common/io.py
dcmagick/common/proxy.py
dcmagick/common/query.py
dcmagick/common/uid.py
dcmagick/common/window.py
dcmagick/convert/__init__.py
dcmagick/convert/convert.py
dcmagick/dump/__init__.py
dcmagick/dump/dump.py
dcmagick/dump/json.py
dcmagick/dump/pretty.py
dcmagick/dump/terminal.py
dcmagick/find/__init__.py
dcmagick/find/find.py
dcmagick/util.py
dcmagick-0.1.0.dist-info/entry_points.txt
dcmagick-0.1.0.dist-info/LICENSE
dcmagick-0.1.0.dist-info/WHEEL
dcmagick-0.1.0.dist-info/METADATA
dcmagick-0.1.0.dist-info/RECORD
