Metadata-Version: 2.1
Name: dcmagick
Version: 0.1.0
Summary: Python libray for displaying images on terminal
Home-page: https://github.com/ar90n/dcmagick
License: MIT
Keywords: dicom,terminal,graphics
Author: Masahiro Wada
Author-email: argon.argon.argon@gmail.com
Requires-Python: >=3.6,<4.0
Classifier: License :: OSI Approved :: MIT License
Classifier: Programming Language :: Python :: 3
Classifier: Programming Language :: Python :: 3.6
Classifier: Programming Language :: Python :: 3.7
Classifier: Programming Language :: Python :: 3.8
Requires-Dist: click (>=7.0,<8.0)
Requires-Dist: joblib (>=0.14.1,<0.15.0)
Requires-Dist: numpy (>=1.18.1,<2.0.0)
Requires-Dist: pydicom (>=1.4.1,<2.0.0)
Requires-Dist: scikit-image (>=0.16.2,<0.17.0)
Requires-Dist: teimpy (>=0.1.1,<0.2.0)
Project-URL: Repository, https://github.com/ar90n/dcmagick
